compneuro_tools/atlas_overlap.py
compneuro_tools/cluster_correction_mc.py
compneuro_tools/fit_glm.py
compneuro_tools/match_groups_in_table.py
compneuro_tools/atlases/__init__.py
compneuro_tools/atlases/xtract.py
compneuro_tools-0.1.2.dist-info/METADATA
compneuro_tools-0.1.2.dist-info/WHEEL
compneuro_tools-0.1.2.dist-info/entry_points.txt
compneuro_tools-0.1.2.dist-info/top_level.txt
compneuro_tools-0.1.2.dist-info/RECORD
