Metadata-Version: 2.4
Name: compneuro-tools
Version: 0.1.2
Summary: A collection of simple yet useful "brain gardening tools" for my PhD works in CompNeuroBilbaoLab.
Author-email: Iñigo Tellaetxe Elorriaga <inigotellaetxe@gmail.com>
Maintainer-email: Iñigo Tellaetxe Elorriaga <inigotellaetxe@gmail.com>
License-Expression: Apache-2.0
Keywords: brain,neuroscience,computational neuroimaging
Classifier: Development Status :: 3 - Alpha
Classifier: Intended Audience :: Science/Research
Classifier: Programming Language :: Python :: 3.11
Classifier: Natural Language :: English
Classifier: Operating System :: POSIX :: Linux
Classifier: Operating System :: MacOS
Requires-Python: >=3.11
Requires-Dist: ipykernel>=6.29.5
Requires-Dist: matplotlib>=3.10.1
Requires-Dist: nilearn>=0.11.1
Requires-Dist: polars>=1.26.0
Requires-Dist: ruff>=0.11.8
Requires-Dist: scipy
